sitecustomize.py
sinq/__init__.py
sinq/_autopatch.py
sinq/awq.py
sinq/bitpack.py
sinq/dual_shift.py
sinq/hf_io.py
sinq/optimize.py
sinq/patch_model.py
sinq/quantizer.py
sinq/sinkhorn.py
sinq/sinqlinear.py
sinq/utils.py
sinq-0.1.6.post1.dist-info/licenses/LICENSE.txt
sinq-0.1.6.post1.dist-info/METADATA
sinq-0.1.6.post1.dist-info/WHEEL
sinq-0.1.6.post1.dist-info/top_level.txt
sinq-0.1.6.post1.dist-info/RECORD
