Metadata-Version: 2.4
Name: sinq
Version: 0.1.6.post1
Summary: SINQ quantization I/O for Hugging Face Transformers
Author-email: Chiara Boretti <chiara.boretti.95@gmail.com>
License: Apache-2.0
Project-URL: Homepage, https://github.com/huawei-csl/SINQ
Project-URL: Issues, https://github.com/huawei-csl/SINQ/issues
Keywords: transformers,quantization,huggingface,LLM
Classifier: Programming Language :: Python :: 3
Classifier: License :: OSI Approved :: Apache Software License
Classifier: Operating System :: OS Independent
Requires-Python: >=3.8
License-File: LICENSE.txt
Requires-Dist: transformers>=4.41
Requires-Dist: huggingface_hub>=0.22
Requires-Dist: torch>=2.1
Requires-Dist: safetensors>=0.4.2
Requires-Dist: hf_transfer>=0.1.9
Requires-Dist: einops>=0.8.1
Requires-Dist: datasets
Requires-Dist: numpy
Requires-Dist: scipy>=1.13.1
Requires-Dist: torchaudio>=2.8.0
Requires-Dist: torchvision>=0.23.0
Requires-Dist: lm_eval>=0.4.8
Requires-Dist: termcolor
Requires-Dist: gemlite==0.5.1.post1
Dynamic: license-file
